AUTHORS
LICENSE
MANIFEST.in
README.rst
setup.py
tusk/__init__.py
tusk.egg-info/PKG-INFO
tusk.egg-info/SOURCES.txt
tusk.egg-info/dependency_links.txt
tusk.egg-info/not-zip-safe
tusk.egg-info/requires.txt
tusk.egg-info/top_level.txt